logtrapz/__init__.py
logtrapz/jax.py
logtrapz/logtrapz.py
logtrapz-0.3.dist-info/LICENSE
logtrapz-0.3.dist-info/METADATA
logtrapz-0.3.dist-info/WHEEL
logtrapz-0.3.dist-info/top_level.txt
logtrapz-0.3.dist-info/RECORD
