Metadata-Version: 2.1
Name: logtrapz
Version: 0.3
Summary: logtrapz
Home-page: https://github.com/mdmould/logtrapz
Author: Matthew Mould
Author-email: mattdmould@gmail.com
License: MIT
Requires-Python: >=3.7
License-File: LICENSE
Requires-Dist: numpy
Requires-Dist: scipy
